refparse/__init__.py
refparse/cssci.py
refparse/scopus.py
refparse/wos.py
refparse-0.5.0.dist-info/LICENSE
refparse-0.5.0.dist-info/METADATA
refparse-0.5.0.dist-info/WHEEL
refparse-0.5.0.dist-info/top_level.txt
refparse-0.5.0.dist-info/RECORD
