Metadata-Version: 2.1
Name: refparse
Version: 0.5.0
Summary: A Python library to parse bibliographic references
Author-email: WangK2 <kw221225@gmail.com>
License: MIT
Project-URL: Repository, https://github.com/doublessay/refparse
Classifier: Development Status :: 3 - Alpha
Classifier: Intended Audience :: Science/Research
Classifier: License :: OSI Approved :: MIT License
Classifier: Programming Language :: Python :: 3
Classifier: Programming Language :: Python :: 3 :: Only
Classifier: Programming Language :: Python :: 3.9
Classifier: Programming Language :: Python :: 3.10
Classifier: Programming Language :: Python :: 3.11
Classifier: Programming Language :: Python :: 3.12
Classifier: Operating System :: OS Independent
Classifier: Topic :: Scientific/Engineering :: Information Analysis
Classifier: Typing :: Typed
Requires-Python: >=3.9
License-File: LICENSE
